{
    "@context": [
        "http://iiif.io/api/presentation/2/context.json"
    ],
    "@id": "http://evil-manifests.davidnewbury.com/iiif/garden/everything_a_list.json",
    "@type": [
        "sc:Manifest"
    ],
    "attribution": [
        "Provided by Example Organization"
    ],
    "description": [
        "A longer description of this example book. It should give some real information."
    ],
    "label": [
        "Book 1"
    ],
    "license": [
        "https://creativecommons.org/publicdomain/zero/1.0/"
    ],
    "logo": [
        "http://evil-manifests.davidnewbury.com/images/logo.jpg"
    ],
    "metadata": [
        {
            "label": "Author",
            "value": "Anne Author"
        },
        {
            "label": "Published",
            "value": [
                {
                    "@language": "en",
                    "@value": "Paris, circa 1400"
                },
                {
                    "@language": "fr",
                    "@value": "Paris, environ 14eme siecle"
                }
            ]
        }
    ],
    "navDate": "1856-01-01T00:00:00Z",
    "related": [
        {
            "@id": "http://example/related/other.pdf",
            "format": "application/pdf",
            "label": "A Related Document"
        }
    ],
    "rendering": [
        {
            "@id": "http://example.org/iiif/book1.pdf",
            "format": "application/pdf",
            "label": "Download as PDF"
        }
    ],
    "seeAlso": [
        {
            "@id": "http://example.org/library/catalog/book1.marc",
            "format": "application/marc",
            "profile": "http://example.org/profiles/marc21"
        }
    ],
    "sequences": [
        {
            "@id": "http://evil-manifests.davidnewbury.com/iiif/garden/sequence/default.json",
            "@type": [
                "sc:Sequence"
            ],
            "canvases": [
                {
                    "@id": "http://evil-manifests.davidnewbury.com/iiif/garden/canvas/front.json",
                    "@type": [
                        "sc:Canvas"
                    ],
                    "height": 1574,
                    "images": [
                        {
                            "@type": [
                                "oa:Annotation"
                            ],
                            "motivation": [
                                "sc:painting"
                            ],
                            "on": [
                                "http://evil-manifests.davidnewbury.com/iiif/garden/canvas/front.json"
                            ],
                            "resource": [
                                {
                                    "@id": "http://evil-manifests.davidnewbury.com/iiif/images/garden-1/full/full/0/default.jpg",
                                    "@type": [
                                        "dctypes:Image"
                                    ],
                                    "format": "image/jpeg",
                                    "height": 1574,
                                    "service": [
                                        {
                                            "@context": "http://iiif.io/api/image/2/context.json",
                                            "@id": "http://evil-manifests.davidnewbury.com/iiif/images/garden-1",
                                            "profile": "http://iiif.io/api/image/2/level0.json"
                                        }
                                    ],
                                    "width": 2952
                                }
                            ]
                        }
                    ],
                    "label": "p. 1",
                    "otherContent": [
                        {
                            "@id": "http://example.org/iiif/book1/list/p1",
                            "@type": "sc:AnnotationList",
                            "within": [
                                {
                                    "@id": "http://example.org/iiif/book1/layer/l1",
                                    "@type": [
                                        "sc:Layer"
                                    ],
                                    "label": [
                                        "Example Layer"
                                    ]
                                }
                            ]
                        }
                    ],
                    "width": 2952
                }
            ],
            "label": [
                "Current Page Order"
            ],
            "viewingDirection": "left-to-right",
            "viewingHint": [
                "paged"
            ]
        }
    ],
    "service": [
        {
            "@context": "http://example.org/ns/jsonld/context.json",
            "@id": "http://example.org/service/example",
            "profile": "http://example.org/docs/example-service.html"
        }
    ],
    "structures": [
        {
            "@id": "http://evil-manifests.davidnewbury.com/iiif/garden/range/range1.json",
            "@type": "sc:Range",
            "canvases": [
                "http://evil-manifests.davidnewbury.com/iiif/garden/canvas/front.json"
            ],
            "label": "Introduction"
        }
    ],
    "thumbnail": [
        "http://evil-manifests.davidnewbury.com/iiif/images/garden-1/full/250,/0/default.jpg"
    ],
    "viewingDirection": "left-to-right",
    "viewingHint": [
        "continuous"
    ],
    "within": [
        "http://evil-manifests.davidnewbury.com/iiif/images/top.json"
    ]
}